{"trial_id": "43", "hyperparameters": {"space": [{"class_name": "Int", "config": {"name": "units1", "default": null, "conditions": [], "min_value": 3, "max_value": 24, "step": 5, "sampling": "linear"}}, {"class_name": "Choice", "config": {"name": "acttype", "default": "sigmoid", "conditions": [], "values": ["sigmoid", "relu", "softmax"], "ordered": false}}, {"class_name": "Float", "config": {"name": "lr", "default": 0.05, "conditions": [], "min_value": 0.05, "max_value": 0.3, "step": null, "sampling": "log"}}], "values": {"units1": 8, "acttype": "sigmoid", "lr": 0.05468617738632212}}, "metrics": {"metrics": {"loss": {"direction": "min", "observations": [{"value": [804.1906433105469], "step": 9}]}, "mse": {"direction": "min", "observations": [{"value": [804.1906433105469], "step": 9}]}, "val_loss": {"direction": "min", "observations": [{"value": [551.5864562988281], "step": 9}]}, "val_mse": {"direction": "min", "observations": [{"value": [551.5864562988281], "step": 9}]}}}, "score": 551.5864562988281, "best_step": 9, "status": "COMPLETED", "message": null}